setup.py
./hamunafs/__init__.py
./hamunafs/client.py
./hamunafs/conf.py
./hamunafs/server.py
./hamunafs/backends/__init__.py
./hamunafs/backends/base.py
./hamunafs/backends/bk_minio.py
./hamunafs/backends/bk_qiniu.py
./hamunafs/backends/bk_share.py
./hamunafs/backends/bk_wy.py
./hamunafs/backends/fetcher.py
./hamunafs/net/__init__.py
./hamunafs/net/api.py
./hamunafs/sqlite/__init__.py
./hamunafs/tuchuang/__init__.py
./hamunafs/tuchuang/tucang.py
./hamunafs/utils/__init__.py
./hamunafs/utils/cachemanager.py
./hamunafs/utils/img_compressor.py
./hamunafs/utils/minio.py
./hamunafs/utils/minio_async.py
./hamunafs/utils/mqtt.py
./hamunafs/utils/nsqmanager.py
./hamunafs/utils/redisutil.py
./hamunafs/utils/singleton_wrapper.py
./hamunafs/utils/timeutil.py
hmfs.egg-info/PKG-INFO
hmfs.egg-info/SOURCES.txt
hmfs.egg-info/dependency_links.txt
hmfs.egg-info/requires.txt
hmfs.egg-info/top_level.txt