Metadata-Version: 2.1
Name: hmfs
Version: 1.1.6132
Summary: Distributed filesystem for Hamuna AI
Home-page: https://www.hamuna.club
Author: O.Push
Author-email: opush.developer@outlook.com
License: MIT
